gedcomx_v1/__init__.py
gedcomx_v1/_utila.py
gedcomx_v1/dateformal.py
gedcomx_v1/fs_session.py
gedcomx_v1/gedcomx.py
gedcomx_v1/json.py
gedcomx_v1/xml.py
gedcomx_v1-1.0.24.dist-info/licenses/LICENSE
gedcomx_v1-1.0.24.dist-info/METADATA
gedcomx_v1-1.0.24.dist-info/WHEEL
gedcomx_v1-1.0.24.dist-info/top_level.txt
gedcomx_v1-1.0.24.dist-info/RECORD
