Metadata-Version: 2.4
Name: gedcomx_v1
Version: 1.0.24
Summary: gedcomx_v1
Home-page: https://github.com/jmichault/gedcomx
Author: Jean Michault
Author-email: author@example.com
License: GNU General Public License v3.0
Project-URL: Bug Tracker, https://github.com/jmichault/gedcomx/issues
Keywords: genealogio,gedcomx
Classifier: Programming Language :: Python :: 3
Classifier: License :: OSI Approved :: GNU General Public License v3 (GPLv3)
Classifier: Operating System :: POSIX :: Linux
Requires-Python: >=3.7
License-File: LICENSE
Requires-Dist: requests
Dynamic: license-file
